[
    {
        "area": "Agricultura",
        "total": "0%",
        "nota": ""
    },
    {
        "area": "Ciencia y Tecnología",
        "total": "0%",
        "nota": ""
    },
    {
        "area": "Cultura y Patrimonio",
        "total": "20%",
        "nota": ""
    },
    {
        "area": "Democracia",
        "total": "85%",
        "nota": ""
    },
    {
        "area": "Desarrollo social",
        "total": "0%",
        "nota": ""
    },
    {
        "area": "Economía",
        "total": "45%",
        "nota": ""
    },
    {
        "area": "Educación",
        "total": "73%",
        "nota": ""
    },
    {
        "area": "Energía",
        "total": "60%",
        "nota": ""
    },
    {
        "area": "Equidad de Género",
        "total": "70%",
        "nota": ""
    },
    {
        "area": "Estado ",
        "total": "45%",
        "nota": ""
    },
    {
        "area": "Infancia y Juventud",
        "total": "40%",
        "nota": ""
    },
    {
        "area": "Justicia y DDHH",
        "total": "51%",
        "nota": ""
    },
    {
        "area": "Medio Ambiente",
        "total": "40%",
        "nota": ""
    },
    {
        "area": "Mineria",
        "total": "0%",
        "nota": ""
    },
    {
        "area": "Obras Públicas",
        "total": "40%",
        "nota": ""
    },
    {
        "area": "Pueblos originarios",
        "total": "20%",
        "nota": ""
    },
    {
        "area": "Salud",
        "total": "0%",
        "nota": ""
    },
    {
        "area": "Trabajo y Previsión Social",
        "total": "98%",
        "nota": ""
    },
    {
        "area": "Vivienda y Urbanismo",
        "total": "40%",
        "nota": ""
    }
]